autocrop/__init__.py
autocrop/__version__.py
autocrop/autocrop.py
autocrop/cli.py
autocrop/constants.py
autocrop/haarcascade_frontalface_default.xml
autocrop-1.3.0.dist-info/LICENSE
autocrop-1.3.0.dist-info/LICENSE-3RD-PARTY.txt
autocrop-1.3.0.dist-info/METADATA
autocrop-1.3.0.dist-info/WHEEL
autocrop-1.3.0.dist-info/entry_points.txt
autocrop-1.3.0.dist-info/top_level.txt
autocrop-1.3.0.dist-info/RECORD
