Metadata-Version: 2.1
Name: autocrop
Version: 1.3.0
Summary: Automatically crops faces from batches of pictures
Home-page: https://github.com/leblancfg/autocrop
Author: François Leblanc
Author-email: leblancfg@gmail.com
License: BSD 2-Clause
Platform: UNKNOWN
Classifier: License :: OSI Approved :: BSD License
Classifier: Programming Language :: Python
Classifier: Programming Language :: Python :: 3.7
Classifier: Programming Language :: Python :: 3.8
Classifier: Programming Language :: Python :: 3.9
Classifier: Programming Language :: Python :: 3.10
Classifier: Programming Language :: Python :: 3 :: Only
Requires-Python: >=3.6
License-File: LICENSE
License-File: LICENSE-3RD-PARTY.txt
